parsec/__init__.py
parsec/logging.py
parsec/cache/__init__.py
parsec/cache/base.py
parsec/cache/keys.py
parsec/cache/memory.py
parsec/core/__init__.py
parsec/core/base.py
parsec/core/schemas.py
parsec/enforcement/engine.py
parsec/enforcement/streaming_engine.py
parsec/models/__init__.py
parsec/models/adapters/__init__.py
parsec/models/adapters/anthropic_adapter.py
parsec/models/adapters/gemini_adapter.py
parsec/models/adapters/ollama_adapter.py
parsec/models/adapters/openai_adapter.py
parsec/prompts/__init__.py
parsec/prompts/analytics.py
parsec/prompts/manager.py
parsec/prompts/registry.py
parsec/prompts/template.py
parsec/prompts/testing.py
parsec/resilience/__init__.py
parsec/resilience/backoff.py
parsec/resilience/circuit_breaker.py
parsec/resilience/failover.py
parsec/resilience/retry.py
parsec/training/__init__.py
parsec/training/collector.py
parsec/training/schemas.py
parsec/utils/__init__.py
parsec/utils/partial_json.py
parsec/validators/__init__.py
parsec/validators/base_validator.py
parsec/validators/json_validator.py
parsec/validators/pydantic_validator.py
parsec/validators/repair_utils.py
parsec_llm-0.2.1.dist-info/licenses/LICENSE
parsec_llm-0.2.1.dist-info/METADATA
parsec_llm-0.2.1.dist-info/WHEEL
parsec_llm-0.2.1.dist-info/top_level.txt
parsec_llm-0.2.1.dist-info/RECORD
