Metadata-Version: 2.4
Name: parsec-llm
Version: 0.2.1
Summary: Lightweight orchestration toolkit to generate, validate, repair and enforce structured output from LLMs
Author-email: Oliver Kwun-Morfitt <oliverkwunmorfitt@gmail.com>
Maintainer-email: Oliver Kwun-Morfitt <oliverkwunmorfitt@gmail.com>
License: MIT
Project-URL: Homepage, https://parsec.olliekm.com
Project-URL: Repository, https://github.com/olliekm/parsec
Project-URL: Issues, https://github.com/olliekm/parsec/issues
Project-URL: Documentation, https://parsec.olliekm.com/docs
Keywords: llm,structured-output,validation,json-schema,openai,anthropic,resilience,circuit-breaker,failover,analytics,a-b-testing,prompt-templates
Classifier: Development Status :: 3 - Alpha
Classifier: Intended Audience :: Developers
Classifier: License :: OSI Approved :: MIT License
Classifier: Programming Language :: Python :: 3
Classifier: Programming Language :: Python :: 3.9
Classifier: Programming Language :: Python :: 3.10
Classifier: Programming Language :: Python :: 3.11
Classifier: Programming Language :: Python :: 3.12
Classifier: Topic :: Software Development :: Libraries :: Python Modules
Requires-Python: >=3.9
License-File: LICENSE
Requires-Dist: openai>=1.0.0
Requires-Dist: anthropic>=0.18.0
Requires-Dist: google-generativeai>=0.3.0
Requires-Dist: pydantic>=2.0.0
Requires-Dist: jsonschema>=4.0.0
Requires-Dist: aiohttp>=3.9.0
Requires-Dist: pyyaml>=6.0.0
Requires-Dist: scipy>=1.10.0
Provides-Extra: dev
Requires-Dist: pytest>=7.0.0; extra == "dev"
Requires-Dist: pytest-asyncio>=0.21.0; extra == "dev"
Requires-Dist: pytest-cov>=4.0.0; extra == "dev"
Dynamic: license-file
